gotstate/__init__.py
gotstate/core/__init__.py
gotstate/core/actions.py
gotstate/core/base.py
gotstate/core/errors.py
gotstate/core/events.py
gotstate/core/guards.py
gotstate/core/hooks.py
gotstate/core/state_machine.py
gotstate/core/states.py
gotstate/core/transitions.py
gotstate/core/validations.py
gotstate/plugins/__init__.py
gotstate/plugins/custom_actions.py
gotstate/plugins/custom_guards.py
gotstate/runtime/__init__.py
gotstate/runtime/async_support.py
gotstate/runtime/concurrency.py
gotstate/runtime/context.py
gotstate/runtime/event_queue.py
gotstate/runtime/executor.py
gotstate/runtime/graph.py
gotstate/runtime/state_history.py
gotstate/runtime/timers.py
gotstate-1.0.4.dist-info/LICENSE
gotstate-1.0.4.dist-info/METADATA
gotstate-1.0.4.dist-info/WHEEL
gotstate-1.0.4.dist-info/top_level.txt
gotstate-1.0.4.dist-info/RECORD
