Metadata-Version: 2.2
Name: gotstate
Version: 1.0.4
Summary: A hierarchical finite state machine library
Author-email: Brad Edwards <brad@keplerops.com>
License: MIT
Project-URL: Homepage, https://github.com/Brad-Edwards/gotstate
Project-URL: Repository, https://github.com/Brad-Edwards/gotstate
Project-URL: Documentation, https://github.com/Brad-Edwards/gotstate#readme
Project-URL: Changelog, https://github.com/Brad-Edwards/gotstate/blob/main/CHANGELOG.md
Keywords: state-machine,hsm,finite-state-machine,hierarchical-state-machine
Classifier: Development Status :: 5 - Production/Stable
Classifier: Intended Audience :: Developers
Classifier: License :: OSI Approved :: MIT License
Classifier: Programming Language :: Python :: 3
Classifier: Programming Language :: Python :: 3.8
Classifier: Programming Language :: Python :: 3.9
Classifier: Programming Language :: Python :: 3.10
Classifier: Topic :: Software Development :: Libraries :: Python Modules
Requires-Python: >=3.8
License-File: LICENSE
Requires-Dist: pydantic>=2.9.2
Requires-Dist: typing_extensions>=4.12.2
